{
  "parent": "minecraft:recipes/root",
  "criteria": {
    "has_the_recipe": {
      "conditions": {
        "recipe": "buildersparadise:waxed_moderately_rusted_iron_tile_slab"
      },
      "trigger": "minecraft:recipe_unlocked"
    },
    "has_waxed_moderately_rusted_iron_tiles": {
      "conditions": {
        "items": [
          {
            "items": "buildersparadise:waxed_moderately_rusted_iron_tiles"
          }
        ]
      },
      "trigger": "minecraft:inventory_changed"
    }
  },
  "requirements": [
    [
      "has_the_recipe",
      "has_waxed_moderately_rusted_iron_tiles"
    ]
  ],
  "rewards": {
    "recipes": [
      "buildersparadise:waxed_moderately_rusted_iron_tile_slab"
    ]
  }
}